CHANGES.txt
COPYRIGHT.txt
LICENSE.txt
README.txt
buildout.cfg
setup.py
bootstrap/bootstrap.py
docs/source/README.rst
docs/source/bugs.rst
docs/source/changes.rst
docs/source/conf.py
docs/source/contents.rst
docs/source/copyright.rst
docs/source/index.rst
docs/source/intro.rst
docs/source/license.rst
docs/source/_templates/layout.html
docs/source/_templates/main.html
docs/source/api/api_app.rst
docs/source/api/api_configuration.rst
docs/source/api/api_http.rst
docs/source/api/api_iowatchdog.rst
docs/source/api/api_util.rst
docs/source/api/index.rst
src/odls/__init__.py
src/odls.client.egg-info/PKG-INFO
src/odls.client.egg-info/SOURCES.txt
src/odls.client.egg-info/dependency_links.txt
src/odls.client.egg-info/entry_points.txt
src/odls.client.egg-info/namespace_packages.txt
src/odls.client.egg-info/requires.txt
src/odls.client.egg-info/top_level.txt
src/odls/client/README.txt
src/odls/client/__init__.py
src/odls/client/app.py
src/odls/client/configuration.py
src/odls/client/default.ini
src/odls/client/http.py
src/odls/client/iowatchdog.py
src/odls/client/logger.py
src/odls/client/logging.conf
src/odls/client/main.py
src/odls/client/parsermanager.py
src/odls/client/test_odlsclient.py
src/odls/client/util.py
src/odls/client/tests/__init__.py
src/odls/client/tests/indexer_ini.template
src/odls/client/tests/test_configuration.py
src/odls/client/tests/test_configuration.txt
src/odls/client/tests/test_http.py
src/odls/client/tests/test_httpserver.py
src/odls/client/tests/test_iowatcher.py
src/odls/client/tests/test_logger.py
src/odls/client/tests/test_util.py
src/odls/client/tests/testing.py