Metadata-Version: 1.0
Name: odls.client
Version: 0.1
Summary: A Python client for ODLS
Home-page: http://pypi.python.org/pypi/odls.client
Author: Uli Fouquet
Author-email: uli at gnufix.de
License: UNKNOWN
Keywords: ODLS client server filesystem indexer odls_client
Platform: UNKNOWN
Classifier: Development Status :: 3 - Alpha
Classifier: Environment :: Console
Classifier: Framework :: Buildout
Classifier: Intended Audience :: End Users/Desktop
Classifier: Intended Audience :: System Administrators
Classifier: Operating System :: POSIX :: Linux
Classifier: Programming Language :: Python
Classifier: Topic :: Internet :: WWW/HTTP :: Indexing/Search
Classifier: Topic :: Text Processing :: Indexing
Classifier: License :: OSI Approved :: GNU General Public License (GPL)
